README.rst
pyturing.py
setup.py
pyturing.egg-info/PKG-INFO
pyturing.egg-info/SOURCES.txt
pyturing.egg-info/dependency_links.txt
pyturing.egg-info/top_level.txt